setup.py
python3_django_user_roles.egg-info/PKG-INFO
python3_django_user_roles.egg-info/SOURCES.txt
python3_django_user_roles.egg-info/dependency_links.txt
python3_django_user_roles.egg-info/top_level.txt
userroles/__init__.py
userroles/decorators.py
userroles/models.py
userroles/tests.py
userroles/utils.py
userroles/migrations/0001_initial.py
userroles/migrations/__init__.py
userroles/testapp/__init__.py
userroles/testapp/models.py
userroles/testapp/urls.py
userroles/testapp/views.py