Metadata-Version: 1.0
Name: python3-django-user-roles
Version: 0.1.0
Summary: Simple role-based user permissions for Django.
Home-page: http://github.com/heyitsjames/django-user-roles
Author: Tom Christie
Author-email: tom@tomchristie.com
License: BSD
Platform: UNKNOWN
